<?xml version="1.0" encoding="utf-8"?>
<technologies>
  <category>
    <type>Manorialism</type>
    <master>Steward</master>
    <eras>
        <merovingian>
            <technology>Open Field System</technology>      
        </merovingian> 
        <carolingian>
            <technology>Three Field System</technology>      
        </carolingian> 
        <viking>
            <technology>Horse Collar</technology> 
        </viking> 
        <ottonian>
            <technology>Agronomics</technology> 
        </ottonian>
        <romanesque>
            <technology>Post Mill</technology> 
        </romanesque>
        <norman>
            <technology>Basket Press</technology> 
        </norman>
        <gothic>
            <technology>Charter Rolls</technology> 
        </gothic>
        <rayonnant>
            <technology>Gothic Urbanization</technology> 
        </rayonnant>
        <flamboyant>
            <technology>Paper Mill</technology> 
        </flamboyant>
        <italian>
            <technology>Renaissance Urbanization</technology> 
        </italian>
        <maritime>
            <technology>Renaissance Viticulture</technology> 
        </maritime> 
    </eras>
  </category>
  <category>
    <type>Crafts</type>
    <master>Steward</master>
    <eras>
        <merovingian>
            <technology>Hop Cultivation</technology>      
        </merovingian> 
        <carolingian>
            <technology>Arab Caravan</technology>      
        </carolingian> 
        <viking>
            <technology>Distillation</technology> 
        </viking> 
        <ottonian>
            <technology>Horizontal Loom</technology> 
        </ottonian>
        <romanesque>
            <technology>Spinning Wheel</technology> 
        </romanesque>
        <norman>
            <technology>Blast Furnace</technology> 
        </norman>
        <gothic>
            <technology>Major Guilds</technology> 
        </gothic>
        <rayonnant>
            <technology>Lesser Guilds</technology> 
        </rayonnant>
        <flamboyant>
            <technology>Canada System</technology> 
        </flamboyant>
        <italian>
            <technology>Maiolica</technology> 
        </italian>
        <maritime>
            <technology>Stagecoach</technology> 
        </maritime> 
    </eras>
  </category>
  <category>
    <type>Feudalism</type>
    <master>Steward</master>
    <eras>
        <merovingian>
            <technology>Merovingian Fealty</technology>      
        </merovingian> 
        <carolingian>
            <technology>Lyric Poetry</technology>      
        </carolingian> 
        <viking>
            <technology>Viking Fealty</technology> 
        </viking> 
        <ottonian>
            <technology>Lombard Commune</technology> 
        </ottonian>
        <romanesque>
            <technology>Courtly Love</technology> 
        </romanesque>
        <norman>
            <technology>Norman Commune</technology> 
        </norman>
        <gothic>
            <technology>Great Council</technology> 
        </gothic>
        <rayonnant>
            <technology>Fables</technology> 
        </rayonnant>
        <flamboyant>
            <technology>Table Games</technology> 
        </flamboyant>
        <italian>
            <technology>Rondeau</technology> 
        </italian>
        <maritime>
            <technology>Canvas</technology> 
        </maritime> 
    </eras>
  </category>
  <category>
    <type>Scholasticism</type>
    <master>Chancellor</master>
    <eras>
        <merovingian>
            <technology>Lay Investiture</technology>      
        </merovingian> 
        <carolingian>
            <technology>Capitulary</technology>      
        </carolingian> 
        <viking>
            <technology>Algebra</technology> 
        </viking> 
        <ottonian>
            <technology>Scholae</technology> 
        </ottonian>
        <romanesque>
            <technology>Early Scholasticism</technology> 
        </romanesque>
        <norman>
            <technology>Studium Generale</technology> 
        </norman>
        <gothic>
            <technology>Studium Liberalia</technology> 
        </gothic>
        <rayonnant>
            <technology>High Scholasticism</technology> 
        </rayonnant>
        <flamboyant>
            <technology>Studium Humanitas</technology> 
        </flamboyant>
        <italian>
            <technology>Renaissance Scholasticism</technology> 
        </italian>
        <maritime>
            <technology>Conciliarism</technology> 
        </maritime> 
    </eras>
  </category>
  <category>
    <type>Finance</type>
    <master>Treasurer</master>
    <eras>
        <merovingian>
            <technology>Emporium</technology>      
        </merovingian> 
        <carolingian>
            <technology>Chancery</technology>      
        </carolingian> 
        <viking>
            <technology>Urbarium</technology> 
        </viking> 
        <ottonian>
            <technology>Imperial Administration</technology> 
        </ottonian>
        <romanesque>
            <technology>Pancartes</technology> 
        </romanesque>
        <norman>
            <technology>Great Survey</technology> 
        </norman>
        <gothic>
            <technology>Merchant Bank</technology> 
        </gothic>
        <rayonnant>
            <technology>Anchor Currency</technology> 
        </rayonnant>
        <flamboyant>
            <technology>Bookkeeping</technology> 
        </flamboyant>
        <italian>
            <technology>Land Terrier</technology> 
        </italian>
        <maritime>
            <technology>Mercantilism</technology> 
        </maritime> 
    </eras>
  </category>
  <category>
    <type>Wardrobe</type>
    <master>Chamberlain</master>
    <eras>
        <merovingian>
            <technology>Samite Fabric</technology>      
        </merovingian> 
        <carolingian>
            <technology>Damask Fabric</technology>      
        </carolingian> 
        <viking>
            <technology>Velvet Fabric</technology> 
        </viking> 
        <ottonian>
            <technology>Hoftag</technology> 
        </ottonian>
        <romanesque>
            <technology>Palas</technology> 
        </romanesque>
        <norman>
            <technology>Heraldry</technology> 
        </norman>
        <gothic>
            <technology>Chimney</technology> 
        </gothic>
        <rayonnant>
            <technology>Parlor</technology> 
        </rayonnant>
        <flamboyant>
            <technology>Tabard</technology> 
        </flamboyant>
        <italian>
            <technology>Tapestry</technology> 
        </italian>
        <maritime>
            <technology>Cassone</technology> 
        </maritime> 
    </eras>
  </category>
  <category>
    <type>Cavalry</type>
    <master>Constable</master>
    <eras>
        <merovingian>
            <technology>Stirrup</technology>      
        </merovingian> 
        <carolingian>
            <technology>Knighthood</technology>      
        </carolingian> 
        <viking>
            <technology>Horseshoe</technology> 
        </viking> 
        <ottonian>
            <technology>Chevauchee</technology> 
        </ottonian>
        <romanesque>
            <technology>Seljuk Sabre</technology> 
        </romanesque>
        <norman>
            <technology>Turcopole</technology> 
        </norman>
        <gothic>
            <technology>Civalry</technology> 
        </gothic>
        <rayonnant>
            <technology>Jinete</technology> 
        </rayonnant>
        <flamboyant>
            <technology>Hobelar</technology> 
        </flamboyant>
        <italian>
            <technology>Rowel Spurs</technology> 
        </italian>
        <maritime>
            <technology>Gendarme</technology> 
        </maritime> 
    </eras>
  </category>
  <category>
    <type>Helmets</type>
    <master>Marshall</master>
    <eras>
        <merovingian>
            <technology>Merovingian Spangenhelm</technology>      
        </merovingian> 
        <carolingian>
            <technology>Carolingian Spangenhelm</technology>      
        </carolingian> 
        <viking>
            <technology>Nasal Helm</technology> 
        </viking> 
        <ottonian>
            <technology>Yarm Helm</technology> 
        </ottonian>
        <romanesque>
            <technology>Vendel Helm</technology> 
        </romanesque>
        <norman>
            <technology>Kettle Hat</technology> 
        </norman>
        <gothic>
            <technology>Enclosed Helm</technology> 
        </gothic>
        <rayonnant>
            <technology>Great Helm</technology> 
        </rayonnant>
        <flamboyant>
            <technology>Bascinet</technology> 
        </flamboyant>
        <italian>
            <technology>Sallet</technology> 
        </italian>
        <maritime>
            <technology>Armet</technology> 
        </maritime> 
    </eras>
  </category>
  <category>
    <type>Armor</type>
    <master>Marshall</master>
    <eras>
        <merovingian>
            <technology>Merovingian Hauberk</technology>      
        </merovingian> 
        <carolingian>
            <technology>Carolingian Hauberk</technology>      
        </carolingian> 
        <viking>
            <technology>Viking Hauberk</technology> 
        </viking> 
        <ottonian>
            <technology>Ottonian Hauberk</technology> 
        </ottonian>
        <romanesque>
            <technology>Romanesque Hauberk</technology> 
        </romanesque>
        <norman>
            <technology>Jazerant</technology> 
        </norman>
        <gothic>
            <technology>Coat of Plates</technology> 
        </gothic>
        <rayonnant>
            <technology>Brigandine</technology> 
        </rayonnant>
        <flamboyant>
            <technology>Breastplates</technology> 
        </flamboyant>
        <italian>
            <technology>Faulds</technology> 
        </italian>
        <maritime>
            <technology>Plate Armor</technology> 
        </maritime> 
    </eras>
  </category>
  <category>
    <type>Melee_Sword</type>
    <master>Marshall</master>
    <eras>
        <merovingian>
            <technology>Merovingian Sword</technology>      
        </merovingian> 
        <carolingian>
            <technology>Carolingian Sword</technology>      
        </carolingian> 
        <viking>
            <technology>Viking Sword</technology> 
        </viking> 
        <ottonian>
            <technology>Ottonian Sword</technology> 
        </ottonian>
        <romanesque>
            <technology>Knightly Sword</technology> 
        </romanesque>
        <norman>
            <technology>Arming Sword</technology> 
        </norman>
        <gothic>
            <technology>Dagger</technology> 
        </gothic>
        <rayonnant>
            <technology>Longsword</technology> 
        </rayonnant>
        <flamboyant>
            <technology>Fencing Books</technology> 
        </flamboyant>
        <italian>
            <technology>Claymore</technology> 
        </italian>
        <maritime>
            <technology>Great Sword</technology> 
        </maritime> 
    </eras>
  </category>
  <category>
    <type>Melee_Polearm</type>
    <master>Marshall</master>
    <eras>
        <merovingian>
            <technology>Merovingian Bill</technology>      
        </merovingian> 
        <carolingian>
            <technology>Carolingian Bill</technology>      
        </carolingian> 
        <viking>
            <technology>Hafted Axe</technology> 
        </viking> 
        <ottonian>
            <technology>Ottonian Bill</technology> 
        </ottonian>
        <romanesque>
            <technology>Bill Guisarme</technology> 
        </romanesque>
        <norman>
            <technology>Fauchard</technology> 
        </norman>
        <gothic>
            <technology>Routier</technology> 
        </gothic>
        <rayonnant>
            <technology>Bardiche</technology> 
        </rayonnant>
        <flamboyant>
            <technology>Halberd</technology> 
        </flamboyant>
        <italian>
            <technology>Poleaxe</technology> 
        </italian>
        <maritime>
            <technology>Voulge Guisarme</technology> 
        </maritime> 
    </eras>
  </category>
  <category>
    <type>Skirmish</type>
    <master>Marshall</master>
    <eras>
        <merovingian>
            <technology>Francisca</technology>      
        </merovingian> 
        <carolingian>
            <technology>Carolingian Shortbow</technology>      
        </carolingian> 
        <viking>
            <technology>Viking Shortbow</technology> 
        </viking> 
        <ottonian>
            <technology>Crossbow</technology> 
        </ottonian>
        <romanesque>
            <technology>Seljuk Bow</technology> 
        </romanesque>
        <norman>
            <technology>Norman Shortbow</technology> 
        </norman>
        <gothic>
            <technology>Arbalest</technology> 
        </gothic>
        <rayonnant>
            <technology>Pavise</technology> 
        </rayonnant>
        <flamboyant>
            <technology>Longbow</technology> 
        </flamboyant>
        <italian>
            <technology>Culverin</technology> 
        </italian>
        <maritime>
            <technology>Arquebus</technology> 
        </maritime> 
    </eras>
  </category>
  <category>
    <type>Port</type>
    <master>Admiral</master>
    <eras>
        <merovingian>
            <technology>Lapstrake</technology>      
        </merovingian> 
        <carolingian>
            <technology>Portage</technology>      
        </carolingian> 
        <viking>
            <technology>Staple Right</technology> 
        </viking> 
        <ottonian>
            <technology>Byzantine Lateen Rig</technology> 
        </ottonian>
        <romanesque>
            <technology>Customs Post</technology> 
        </romanesque>
        <norman>
            <technology>Factory</technology> 
        </norman>
        <gothic>
            <technology>Sternpost Rudder</technology> 
        </gothic>
        <rayonnant>
            <technology>Portolan Chart</technology> 
        </rayonnant>
        <flamboyant>
            <technology>Portuguese Lateen Rig</technology> 
        </flamboyant>
        <italian>
            <technology>Quarantine</technology> 
        </italian>
        <maritime>
            <technology>Full Rig</technology> 
        </maritime> 
    </eras>
  </category>
  <category>
    <type>Entertainment</type>
    <master>Master of the Revels</master>
    <eras>
        <merovingian>
            <technology>Falconry</technology>      
        </merovingian> 
        <carolingian>
            <technology>Coronation Banquet</technology>      
        </carolingian> 
        <viking>
            <technology>Tourney</technology> 
        </viking> 
        <ottonian>
            <technology>Ceremony</technology> 
        </ottonian>
        <romanesque>
            <technology>Romanesque Fairs</technology> 
        </romanesque>
        <norman>
            <technology>Troubadours</technology> 
        </norman>
        <gothic>
            <technology>Gothic Fairs</technology> 
        </gothic>
        <rayonnant>
            <technology>Joust</technology> 
        </rayonnant>
        <flamboyant>
            <technology>Hastilude</technology> 
        </flamboyant>
        <italian>
            <technology>Saltarello</technology> 
        </italian>
        <maritime>
            <technology>Chamber of Rhetoric</technology> 
        </maritime> 
    </eras>
  </category>
  <category>
    <type>Fortification</type>
    <master>Castellan</master>
    <eras>
        <merovingian>
            <technology>Ribat</technology>      
        </merovingian> 
        <carolingian>
            <technology>Albarrana Tower</technology>      
        </carolingian> 
        <viking>
            <technology>Motte and Bailey</technology> 
        </viking> 
        <ottonian>
            <technology>Enceinte</technology> 
        </ottonian>
        <romanesque>
            <technology>Donjon</technology> 
        </romanesque>
        <norman>
            <technology>Concentric Castle</technology> 
        </norman>
        <gothic>
            <technology>Bastide</technology> 
        </gothic>
        <rayonnant>
            <technology>Barbican</technology> 
        </rayonnant>
        <flamboyant>
            <technology>Kremlin</technology> 
        </flamboyant>
        <italian>
            <technology>Zwinger</technology> 
        </italian>
        <maritime>
            <technology>Roundel</technology> 
        </maritime> 
    </eras>
  </category>
  <category>
    <type>Construction</type>
    <master>Master Mason</master>
    <eras>
        <merovingian>
            <technology>Cloister</technology>      
        </merovingian> 
        <carolingian>
            <technology>Ribbed Vault</technology>      
        </carolingian> 
        <viking>
            <technology>Byzantine Arcade</technology> 
        </viking> 
        <ottonian>
            <technology>Ottonian Arcade</technology> 
        </ottonian>
        <romanesque>
            <technology>Groin Vault</technology> 
        </romanesque>
        <norman>
            <technology>Archivolt</technology> 
        </norman>
        <gothic>
            <technology>Lancet Window</technology> 
        </gothic>
        <rayonnant>
            <technology>Treadwheel Crane</technology> 
        </rayonnant>
        <flamboyant>
            <technology>Fan Vault</technology> 
        </flamboyant>
        <italian>
            <technology>Renaissance Arcade</technology> 
        </italian>
        <maritime>
            <technology>Renaissance Dome</technology> 
        </maritime> 
    </eras>
  </category>
  <category>
    <type>Siegecraft</type>
    <master>Siege Engineer</master>
    <eras> 
        <merovingian>
            <technology>Merovingian Mangonel</technology>      
        </merovingian> 
        <carolingian>
            <technology>Arab Mangonel</technology>      
        </carolingian> 
        <viking>
            <technology>Viking Mangonel</technology> 
        </viking> 
        <ottonian>
            <technology>Ottonian Mangonel</technology> 
        </ottonian>
        <romanesque>
            <technology>Hoarding</technology> 
        </romanesque>
        <norman>
            <technology>Springald</technology> 
        </norman>
        <gothic>
            <technology>Counterpoise Trebuchet</technology> 
        </gothic>
        <rayonnant>
            <technology>Gunpowder</technology> 
        </rayonnant>
        <flamboyant>
            <technology>Cannon</technology> 
        </flamboyant>
        <italian>
            <technology>Gun Loop</technology> 
        </italian>
        <maritime>
            <technology>Bombard</technology> 
        </maritime> 
    </eras>
  </category>
  <category>
    <type>Scriptures</type>
    <master>Chronicler</master>
    <eras>
        <merovingian>
            <technology>Insular Manuscripts</technology>      
        </merovingian> 
        <carolingian>
            <technology>Carolingian Manuscripts</technology>      
        </carolingian> 
        <viking>
            <technology>Byzantine Manuscripts</technology> 
        </viking> 
        <ottonian>
            <technology>Ottonian Manuscripts</technology> 
        </ottonian>
        <romanesque>
            <technology>Romanesque Manuscripts</technology> 
        </romanesque>
        <norman>
            <technology>Norman Manuscripts</technology> 
        </norman>
        <gothic>
            <technology>Gothic Manuscripts</technology> 
        </gothic>
        <rayonnant>
            <technology>Roll of Arms</technology> 
        </rayonnant>
        <flamboyant>
            <technology>Painted Panel Altars</technology> 
        </flamboyant>
        <italian>
            <technology>Renaissance Manuscripts</technology> 
        </italian>
        <maritime>
            <technology>Blockbooks</technology> 
        </maritime> 
    </eras>
  </category>
  <category>
    <type>Monasticism</type>
    <master>Almoner</master>
    <eras>
        <merovingian>
            <technology>Merovingian Relics</technology>      
        </merovingian> 
        <carolingian>
            <technology>Carolingian Relics</technology>      
        </carolingian> 
        <viking>
            <technology>Herbalism</technology> 
        </viking> 
        <ottonian>
            <technology>Pharmacy</technology> 
        </ottonian>
        <romanesque>
            <technology>Medicine</technology> 
        </romanesque>
        <norman>
            <technology>Passagium Generale</technology> 
        </norman>
        <gothic>
            <technology>Morality Play</technology> 
        </gothic>
        <rayonnant>
            <technology>Gothic Mendicant</technology> 
        </rayonnant>
        <flamboyant>
            <technology>Gothic Relics</technology> 
        </flamboyant>
        <italian>
            <technology>Renaissance Mendicant</technology> 
        </italian>
        <maritime>
            <technology>Renaissance Relics</technology> 
        </maritime> 
    </eras>
  </category>
</technologies>